pytorchfire/__about__.py
pytorchfire/__init__.py
pytorchfire/model.py
pytorchfire/trainer.py
pytorchfire/utils.py
pytorchfire-1.0.3.post2.dist-info/METADATA
pytorchfire-1.0.3.post2.dist-info/WHEEL
pytorchfire-1.0.3.post2.dist-info/licenses/LICENSE
pytorchfire-1.0.3.post2.dist-info/RECORD
