Metadata-Version: 2.4
Name: pytorchfire
Version: 1.0.3.post2
Summary: PyTorchFire: A GPU-Accelerated Wildfire Simulator with Differentiable Cellular Automata
Project-URL: Documentation, https://pytorchfire.readthedocs.io/
Project-URL: Issues, https://github.com/xiazeyu/PyTorchFire/issues
Project-URL: Source, https://github.com/xiazeyu/PyTorchFire
Author-email: Zeyu Xia <zeyu.xia@virginia.edu>, Sibo Cheng <sibo.cheng@enpc.fr>
License: MIT License
License-File: LICENSE
Classifier: Environment :: GPU
Classifier: Intended Audience :: Science/Research
Classifier: License :: OSI Approved :: MIT License
Classifier: Operating System :: OS Independent
Classifier: Programming Language :: Python :: 3
Classifier: Topic :: Scientific/Engineering :: Atmospheric Science
Requires-Python: >=3.8
Requires-Dist: einops
Requires-Dist: numpy
Requires-Dist: torch
Provides-Extra: examples
Requires-Dist: einops; extra == 'examples'
Requires-Dist: h5py; extra == 'examples'
Requires-Dist: mpi4py; extra == 'examples'
Requires-Dist: numpy; extra == 'examples'
Requires-Dist: tensorboard; extra == 'examples'
Requires-Dist: torch; extra == 'examples'
Requires-Dist: tqdm; extra == 'examples'
